Metadata-Version: 2.4
Name: covenance-ai
Version: 0.0.1
Summary: Online LLM clients for OpenAI, Google Gemini, Mistral, Anthropic Claude, and OpenRouter (Covenance reservation)
Author: Ilya Kamen
License: MIT
Keywords: anthropic,gemini,llm,mistral,openai,openrouter
Classifier: Programming Language :: Python
Classifier: Programming Language :: Python :: 3
Classifier: Programming Language :: Python :: 3.10
Classifier: Programming Language :: Python :: 3.11
Classifier: Programming Language :: Python :: 3.12
Classifier: Programming Language :: Python :: 3.13
Classifier: Topic :: Software Development :: Libraries :: Python Modules
Classifier: Topic :: Utilities
Requires-Python: >=3.10
Requires-Dist: anthropic
Requires-Dist: google-genai
Requires-Dist: mistralai
Requires-Dist: openai
Requires-Dist: pydantic
Requires-Dist: python-dotenv
Provides-Extra: dev
Requires-Dist: build; extra == 'dev'
Requires-Dist: pre-commit; extra == 'dev'
Requires-Dist: pytest; extra == 'dev'
Requires-Dist: pytest-cov; extra == 'dev'
Requires-Dist: ruff; extra == 'dev'
Requires-Dist: twine; extra == 'dev'
